README.md
setup.py
simono_especificaciones/sensor.py
simono_especificaciones.egg-info/PKG-INFO
simono_especificaciones.egg-info/SOURCES.txt
simono_especificaciones.egg-info/dependency_links.txt
simono_especificaciones.egg-info/top_level.txt
simono_especificaciones/especificaciones/__init__.py
simono_especificaciones/especificaciones/codigos_sensores.py
simono_especificaciones/especificaciones/funciones.py
simono_especificaciones/raspbian/__init__.py
simono_especificaciones/sensores/__init__.py
simono_especificaciones/sensores/raspberry/__init__.py
simono_especificaciones/sensores/raspberry/cpu.py
simono_especificaciones/sensores/raspberry/disco.py
simono_especificaciones/sensores/raspberry/memoria_swap.py
simono_especificaciones/sensores/raspberry/memoria_virtual.py
simono_especificaciones/sensores/raspberry/proceso.py
simono_especificaciones/sensores/raspberry/red.py
simono_especificaciones/sensores/raspberry/temperatura.py
simono_especificaciones/sensores/raspberry/tension.py
simono_especificaciones/sensores/raspberry/tiempo.py
simono_especificaciones/sensores/raspberry/version.py
simono_especificaciones/web/__init__.py