Metadata-Version: 1.1
Name: simono-especificaciones
Version: 0.0.19
Summary: Especificaciones de Sensores para Sistema de Monitoreo de Nodos
Home-page: https://bitbucket.org/lucasecom/especificaciones_simono/src
Author: Ecom Developers
Author-email: simono@ecom.com.ar
License: BSD
Keywords: simono iot raspberry
Platform: UNKNOWN
Classifier: Development Status :: 1 - Planning
Classifier: License :: OSI Approved :: GNU Lesser General Public License v2 (LGPLv2)
Classifier: Programming Language :: Python
Classifier: Programming Language :: Python :: 3.6
Classifier: Topic :: Utilities
